__init__.py
datahub_api_connector/__init__.py
datahub_api_connector/example.py
datahub_api_connector/utils/__init__.py
datahub_api_connector/utils/site_content_duplicator.py
datahub_api_connector-1.2.dist-info/licenses/LICENSE
datahub_api_connector-1.2.dist-info/METADATA
datahub_api_connector-1.2.dist-info/WHEEL
datahub_api_connector-1.2.dist-info/top_level.txt
datahub_api_connector-1.2.dist-info/RECORD
