Metadata-Version: 2.4
Name: datahub-api-connector
Version: 1.2
Summary: Package to help connect to Verity's Data Hub API
Author-email: Verity <support@verity.global>
Maintainer-email: Verity <support@verity.global>
License-Expression: MIT
Project-URL: Homepage, https://github.com/opinum/datahub-api-connector
Project-URL: Bug Tracker, https://github.com/opinum/datahub-api-connector/issues
Keywords: datahub,Data Hub,Verity,Opinum,API,Keycloak
Classifier: Development Status :: 5 - Production/Stable
Classifier: Programming Language :: Python
Requires-Python: >=3.10
License-File: LICENSE
Requires-Dist: requests
Requires-Dist: requests_oauthlib
Requires-Dist: oauthlib
Dynamic: license-file
